heaven/__init__.py
heaven/cli.py
heaven/constants.py
heaven/context.py
heaven/earth.py
heaven/errors.py
heaven/form.py
heaven/mocks.py
heaven/request.py
heaven/response.py
heaven/router.py
heaven/schema.py
heaven/security.py
heaven/tutorials.py
heaven/utils.py
heaven-1.3.6.dist-info/LICENSE
heaven-1.3.6.dist-info/METADATA
heaven-1.3.6.dist-info/WHEEL
heaven-1.3.6.dist-info/entry_points.txt
heaven-1.3.6.dist-info/RECORD
