Metadata-Version: 2.3
Name: heaven
Version: 1.3.6
Summary: Extremely Stupid Simple, Blazing Fast, Get Out of your way immediately Microframework for building Python Web Applications.
License: MIT
Author: Raymond Ortserga
Author-email: ortserga@gmail.com
Requires-Python: >=3.6,<4.0
Classifier: License :: OSI Approved :: MIT License
Classifier: Programming Language :: Python :: 3
Classifier: Programming Language :: Python :: 3.6
Classifier: Programming Language :: Python :: 3.7
Classifier: Programming Language :: Python :: 3.8
Classifier: Programming Language :: Python :: 3.9
Classifier: Programming Language :: Python :: 3.10
Classifier: Programming Language :: Python :: 3.11
Classifier: Programming Language :: Python :: 3.12
Classifier: Programming Language :: Python :: 3.13
Requires-Dist: aiofiles (>=23.0.0,<24.0.0)
Requires-Dist: jinja2 (>=3.1.0,<4.0.0)
Requires-Dist: msgspec (>=0.18.0)
Requires-Dist: rich (>=13.0.0)
Requires-Dist: uvicorn (>=0.14)
Requires-Dist: websockets (>=12.0)
